examples/examples.py
ogmready/__init__.py
ogmready/ogmready.py
ogmready-0.1.6.dist-info/licenses/LICENSE
ogmready-0.1.6.dist-info/METADATA
ogmready-0.1.6.dist-info/WHEEL
ogmready-0.1.6.dist-info/top_level.txt
ogmready-0.1.6.dist-info/RECORD
