Metadata-Version: 2.4
Name: ogmready
Version: 0.1.6
Summary: An object-graph mapper based on owlready2
Author-email: Gianluca Zavan <gianlucagianluca18@gmail.com>
License:                    GNU LESSER GENERAL PUBLIC LICENSE
Project-URL: Homepage, https://github.com/gianzav/ogmready
Classifier: Programming Language :: Python :: 3
Classifier: Operating System :: OS Independent
Requires-Python: >=3.12
License-File: LICENSE
Requires-Dist: owlready2>=0.47
Requires-Dist: inflection
Dynamic: license-file
